{
  "required": true,
  "minVersion": "0.8",
  "package": "de.cadentem.quality_food.mixin",
  "compatibilityLevel": "JAVA_17",
  "refmap": "quality_food.refmap.json",
  "plugin": "de.cadentem.quality_food.mixin.ApplyMixinPlugin",
  "mixins": [
    "AbstractFurnaceBlockEntityMixin",
    "AbstractFurnaceMenuMixin",
    "BlockBehaviourMixin",
    "BlockItemMixin",
    "BlockMixin",
    "CakeBlockMixin",
    "CraftingMenuMixin",
    "EntityMixin",
    "FurnaceResultSlotMixin",
    "GrowingPlantBlockMixin",
    "InventoryMenuMixin",
    "ItemMixin",
    "LevelMixin",
    "PropertiesMixin",
    "ResultSlotMixin",
    "StateDefinitionMixin",
    "StemBlockMixin",
    "SugarCaneBlockMixin",
    "SweetBerryBushBlockMixin",
    "ThrownEggMixin",
    "cratedelight.ModBlocksMixin",
    "create.BasinRecipeMixin",
    "create.HarvesterMovementBehaviourMixin",
    "create.MillstoneBlockEntityMixin",
    "create.RecipeApplierMixin",
    "farmersdelight.BuddingTomatoBlockMixin",
    "farmersdelight.CookingPotBlockEntityMixin",
    "farmersdelight.CookingPotMenuMixin",
    "farmersdelight.CookingPotResultSlotMixin",
    "farmersdelight.CuttingBoardBlockEntityMixin",
    "farmersdelight.FeastBlockMixin",
    "farmersdelight.ModBlocksMixin",
    "farmersdelight.RiceBlockMixin",
    "farmersdelight.RiceRollMedleyBlockMixin",
    "farmersdelight.TextUtilsMixin",
    "farmersdelight.TomatoVineBlockMixin",
    "fastbench.CraftResultSlotExtMixin",
    "fastbench.FastBenchUtilMixin",
    "fastbench.ResultSlotAccess",
    "fastentitytransfer.CommonUtilsMixin",
    "majruszsenchantments.TelekinesisEnchantmentMixin",
    "quark.CompressedBlocksModuleMixin",
    "quark.SimpleHarvestModuleMixin",
    "rightclickharvest.RightClickHarvestModInitMixin",
    "sophisticatedcore.CompactingUpgradeWrapperMixin",
    "sophisticatedcore.CraftingUpgradeContainerAccess",
    "sophisticatedcore.CraftingUpgradeContainerMixin",
    "sophisticatedcore.StorageContainerMenuBaseMixin",
    "toms_storage.CraftingTerminalBlockEntityMixin",
    "toms_storage.CraftingTerminalMenuMixin",
    "vinery.GrapeBushMixin",
    "vinery.GrapeVineBlockMixin",
    "vinery.ObjectRegistryMixin"
  ],
  "client": [
    "client.GuiGraphicsMixin"
  ],
  "injectors": {
    "defaultRequire": 1
  }
}
